PyPixel/__init__.py
PyPixel/imports.py
PyPixel/mcpypixelapi.py
MCPyPixelAPI-0.0.3.dist-info/METADATA
MCPyPixelAPI-0.0.3.dist-info/WHEEL
MCPyPixelAPI-0.0.3.dist-info/top_level.txt
MCPyPixelAPI-0.0.3.dist-info/RECORD
