Metadata-Version: 2.1
Name: MCPyPixelAPI
Version: 0.0.3
Summary: Hypixel API for Python
Home-page: UNKNOWN
Author: William
Author-email: redacted@tocomail.com
License: UNKNOWN
Keywords: python,hypixel,minecraft,api,webapi
Platform: UNKNOWN
Classifier: Intended Audience :: Developers
Classifier: Programming Language :: Python :: 3
Classifier: Operating System :: Unix
Classifier: Operating System :: MacOS :: MacOS X
Classifier: Operating System :: Microsoft :: Windows
